syntrac_opentelemetry/semconv/ai/__init__.py
syntrac_opentelemetry/semconv/ai/version.py
syntrac_opentelemetry_semantic_conventions_ai-0.0.2.dist-info/METADATA
syntrac_opentelemetry_semantic_conventions_ai-0.0.2.dist-info/WHEEL
syntrac_opentelemetry_semantic_conventions_ai-0.0.2.dist-info/RECORD
